{
  "skill_name": "vercel-react-best-practices",
  "skill_path": "/workspace/skills/vercel-labs-agent-skills/skills/react-best-practices",
  "skill_directory": "/workspace/skills/vercel-labs-agent-skills/skills/react-best-practices",
  "is_safe": true,
  "max_severity": "SAFE",
  "findings_count": 0,
  "findings": [],
  "scan_duration_seconds": 0.015465736389160156,
  "duration_ms": 15,
  "analyzers_used": [
    "static_analyzer",
    "behavioral_analyzer",
    "trigger_analyzer"
  ],
  "timestamp": "2026-01-30T22:09:27.353191"
}